AIForged/__init__.py
AIForged/api_client.py
AIForged/configuration.py
AIForged/rest.py
AIForged/api/__init__.py
AIForged/api/account_api.py
AIForged/api/audit_api.py
AIForged/api/bundles_api.py
AIForged/api/classes_api.py
AIForged/api/cloning_api.py
AIForged/api/contact_api.py
AIForged/api/data_set_api.py
AIForged/api/document_api.py
AIForged/api/group_api.py
AIForged/api/log_api.py
AIForged/api/market_place_api.py
AIForged/api/notification_api.py
AIForged/api/param_def_api.py
AIForged/api/parameters_api.py
AIForged/api/payment_api.py
AIForged/api/project_api.py
AIForged/api/reports_api.py
AIForged/api/roles_api.py
AIForged/api/service_type_api.py
AIForged/api/services_api.py
AIForged/api/system_api.py
AIForged/api/user_preferences_api.py
AIForged/api/user_settings_api.py
AIForged/api/verification_api.py
AIForged/api/wizard_api.py
AIForged/api/work_item_api.py
AIForged/models/__init__.py
AIForged/models/action.py
AIForged/models/action1.py
AIForged/models/action2.py
AIForged/models/action3.py
AIForged/models/action4.py
AIForged/models/ai_forged_clone_checks.py
AIForged/models/ai_forged_clone_options.py
AIForged/models/ai_forged_dal_audit_access_type.py
AIForged/models/ai_forged_dal_audit_entity.py
AIForged/models/ai_forged_dal_availability.py
AIForged/models/ai_forged_dal_bundle_type.py
AIForged/models/ai_forged_dal_category_status.py
AIForged/models/ai_forged_dal_charge_status.py
AIForged/models/ai_forged_dal_class_type.py
AIForged/models/ai_forged_dal_contact_status.py
AIForged/models/ai_forged_dal_data_type_category.py
AIForged/models/ai_forged_dal_document_data_type.py
AIForged/models/ai_forged_dal_document_status.py
AIForged/models/ai_forged_dal_enum_type.py
AIForged/models/ai_forged_dal_group_role_status.py
AIForged/models/ai_forged_dal_group_role_type.py
AIForged/models/ai_forged_dal_group_role_user_status.py
AIForged/models/ai_forged_dal_group_status.py
AIForged/models/ai_forged_dal_group_type.py
AIForged/models/ai_forged_dal_grouping_type.py
AIForged-1.0.1.dist-info/METADATA
AIForged-1.0.1.dist-info/WHEEL
AIForged-1.0.1.dist-info/top_level.txt
AIForged-1.0.1.dist-info/RECORD
